pantheon_notebook/__init__.py
pantheon_notebook/_version.py
pantheon_notebook/server.py
pantheon_notebook/labextension/build_log.json
pantheon_notebook/labextension/package.json
pantheon_notebook/labextension/static/lib_index_js.1a522e82a7d283d1b02c.js
pantheon_notebook/labextension/static/lib_index_js.1a522e82a7d283d1b02c.js.map
pantheon_notebook/labextension/static/remoteEntry.c957955b3df4a95b90ea.js
pantheon_notebook/labextension/static/remoteEntry.c957955b3df4a95b90ea.js.map
pantheon_notebook/labextension/static/style.js
pantheon_notebook/labextension/static/style_index_js.44ead5aa6d66710ec3e7.js
pantheon_notebook/labextension/static/style_index_js.44ead5aa6d66710ec3e7.js.map
pantheon_notebook-0.1.3.data/data/etc/jupyter/jupyter_server_config.d/pantheon_notebook.json
pantheon_notebook-0.1.3.data/data/share/jupyter/labextensions/pantheon-notebook/build_log.json
pantheon_notebook-0.1.3.data/data/share/jupyter/labextensions/pantheon-notebook/install.json
pantheon_notebook-0.1.3.data/data/share/jupyter/labextensions/pantheon-notebook/package.json
pantheon_notebook-0.1.3.data/data/share/jupyter/labextensions/pantheon-notebook/static/lib_index_js.1a522e82a7d283d1b02c.js
pantheon_notebook-0.1.3.data/data/share/jupyter/labextensions/pantheon-notebook/static/lib_index_js.1a522e82a7d283d1b02c.js.map
pantheon_notebook-0.1.3.data/data/share/jupyter/labextensions/pantheon-notebook/static/remoteEntry.c957955b3df4a95b90ea.js
pantheon_notebook-0.1.3.data/data/share/jupyter/labextensions/pantheon-notebook/static/remoteEntry.c957955b3df4a95b90ea.js.map
pantheon_notebook-0.1.3.data/data/share/jupyter/labextensions/pantheon-notebook/static/style.js
pantheon_notebook-0.1.3.data/data/share/jupyter/labextensions/pantheon-notebook/static/style_index_js.44ead5aa6d66710ec3e7.js
pantheon_notebook-0.1.3.data/data/share/jupyter/labextensions/pantheon-notebook/static/style_index_js.44ead5aa6d66710ec3e7.js.map
pantheon_notebook-0.1.3.dist-info/METADATA
pantheon_notebook-0.1.3.dist-info/WHEEL
pantheon_notebook-0.1.3.dist-info/entry_points.txt
pantheon_notebook-0.1.3.dist-info/licenses/LICENSE
pantheon_notebook-0.1.3.dist-info/RECORD
