Metadata-Version: 2.4
Name: pantheon-notebook
Version: 0.1.3
Dynamic: Keywords
Summary: A JupyterLab extension for Pantheon CLI integration with floating input widget
Project-URL: Homepage, https://github.com/yourusername/pantheon-notebook
Project-URL: Bug Tracker, https://github.com/yourusername/pantheon-notebook/issues
Project-URL: Repository, https://github.com/yourusername/pantheon-notebook.git
Author-email: Your Name <your.email@example.com>
License: MIT License
License-File: LICENSE
Classifier: Framework :: Jupyter
Classifier: Framework :: Jupyter :: JupyterLab
Classifier: Framework :: Jupyter :: JupyterLab :: 4
Classifier: Framework :: Jupyter :: JupyterLab :: Extensions
Classifier: Framework :: Jupyter :: JupyterLab :: Extensions :: Prebuilt
Classifier: Programming Language :: Python
Classifier: Programming Language :: Python :: 3
Classifier: Programming Language :: Python :: 3.8
Classifier: Programming Language :: Python :: 3.9
Classifier: Programming Language :: Python :: 3.10
Classifier: Programming Language :: Python :: 3.11
Classifier: Programming Language :: Python :: 3.12
Requires-Python: >=3.8
Requires-Dist: jldracula
Requires-Dist: jupyter-server<3,>=1.21
Requires-Dist: tornado>=6.0
